build/combined.v
module clock_divider (
	reset,
	clk_in,
	clk_out
);
	parameter DIV_FACTOR = 50000000;
	input wire reset;
	input wire clk_in;
	output reg clk_out;
	reg [32:0] counter;
	always @(posedge clk_in)
		if (reset) begin
			counter <= 0;
			clk_out <= 0;
		end
		else begin
			counter <= counter + 1;
			if (counter == (DIV_FACTOR - 1)) begin
				clk_out <= ~clk_out;
				counter <= 0;
			end
		end
endmodule
module alu (
	clk,
	reset,
	a_in,
	b_in,
	alu_op,
	latched_result,
	zero_flag,
	carry_flag,
	negative_flag
);
	reg _sv2v_0;
	input wire clk;
	input wire reset;
	localparam signed [31:0] arch_defs_pkg_DATA_WIDTH = 8;
	input wire [7:0] a_in;
	input wire [7:0] b_in;
	input wire [1:0] alu_op;
	output reg [7:0] latched_result;
	output wire zero_flag;
	output wire carry_flag;
	output wire negative_flag;
	reg [arch_defs_pkg_DATA_WIDTH:0] comb_arith_result_i;
	reg [7:0] comp_logic_result_i;
	reg comb_carry_out_i;
	reg [7:0] comb_result_final_i;
	always @(*) begin
		if (_sv2v_0)
			;
		comb_arith_result_i = {9 {1'b0}};
		comp_logic_result_i = {arch_defs_pkg_DATA_WIDTH {1'b0}};
		comb_carry_out_i = 1'b0;
		comb_result_final_i = {arch_defs_pkg_DATA_WIDTH {1'b0}};
		case (alu_op)
			2'b00: comb_arith_result_i = {1'b0, a_in} + {1'b0, b_in};
			2'b01: comb_arith_result_i = ({1'b0, a_in} + {1'b0, ~b_in}) + {{arch_defs_pkg_DATA_WIDTH {1'b0}}, 1'b1};
			2'b10: comp_logic_result_i = a_in & b_in;
			2'b11: comp_logic_result_i = a_in | b_in;
			default:
				;
		endcase
		if ((alu_op == 2'b00) || (alu_op == 2'b01)) begin
			comb_carry_out_i = comb_arith_result_i[arch_defs_pkg_DATA_WIDTH];
			comb_result_final_i = comb_arith_result_i[7:0];
		end
		else begin
			comb_carry_out_i = 1'b0;
			comb_result_final_i = comp_logic_result_i;
		end
	end
	assign carry_flag = comb_carry_out_i;
	assign zero_flag = comb_result_final_i == {arch_defs_pkg_DATA_WIDTH {1'b0}};
	assign negative_flag = comb_result_final_i[7];
	always @(posedge clk)
		if (reset)
			latched_result <= {arch_defs_pkg_DATA_WIDTH {1'b0}};
		else
			latched_result <= comb_result_final_i;
	initial _sv2v_0 = 0;
endmodule
module program_counter (
	clk,
	reset,
	enable,
	load,
	counter_in,
	counter_out
);
	input wire clk;
	input wire reset;
	input wire enable;
	input wire load;
	localparam signed [31:0] arch_defs_pkg_ADDR_WIDTH = 4;
	input wire [3:0] counter_in;
	output reg [3:0] counter_out;
	always @(posedge clk)
		if (reset)
			counter_out <= {arch_defs_pkg_ADDR_WIDTH {1'b0}};
		else if (load)
			counter_out <= counter_in;
		else if (enable)
			counter_out <= counter_out + 1;
endmodule
module ram (
	clk,
	we,
	address,
	data_in,
	data_out
);
	input wire clk;
	input wire we;
	localparam signed [31:0] arch_defs_pkg_ADDR_WIDTH = 4;
	input wire [3:0] address;
	localparam signed [31:0] arch_defs_pkg_DATA_WIDTH = 8;
	input wire [7:0] data_in;
	output wire [7:0] data_out;
	localparam signed [31:0] arch_defs_pkg_RAM_DEPTH = 16;
	reg [7:0] mem [0:15];
	reg [7:0] data_out_i;
	always @(posedge clk) begin
		if (we)
			mem[address] <= data_in;
		data_out_i <= mem[address];
	end
	assign data_out = data_out_i;
	task dump;
		integer j;
		begin
			$display("--- RAM Content Dump ---");
			for (j = 0; j < arch_defs_pkg_RAM_DEPTH; j = j + 1)
				$display("RAM[%0d] = %02h", j, mem[j]);
			$display("--- End RAM Dump ---");
		end
	endtask
	initial $readmemh("../fixture/default_program_synth.hex", mem);
endmodule
module register_instruction (
	clk,
	reset,
	load,
	data_in,
	opcode,
	operand
);
	input wire clk;
	input wire reset;
	input wire load;
	localparam signed [31:0] arch_defs_pkg_DATA_WIDTH = 8;
	input wire [7:0] data_in;
	localparam signed [31:0] arch_defs_pkg_OPCODE_WIDTH = 4;
	output wire [3:0] opcode;
	localparam signed [31:0] arch_defs_pkg_OPERAND_WIDTH = arch_defs_pkg_DATA_WIDTH - arch_defs_pkg_OPCODE_WIDTH;
	output wire [arch_defs_pkg_OPERAND_WIDTH - 1:0] operand;
	reg [(arch_defs_pkg_OPCODE_WIDTH + arch_defs_pkg_OPERAND_WIDTH) - 1:0] instruction;
	function automatic [(arch_defs_pkg_OPCODE_WIDTH + arch_defs_pkg_OPERAND_WIDTH) - 1:0] sv2v_cast_A6704;
		input reg [(arch_defs_pkg_OPCODE_WIDTH + arch_defs_pkg_OPERAND_WIDTH) - 1:0] inp;
		sv2v_cast_A6704 = inp;
	endfunction
	always @(posedge clk)
		if (reset)
			instruction <= 1'sb0;
		else if (load)
			instruction <= sv2v_cast_A6704(data_in);
	assign opcode = instruction[arch_defs_pkg_OPCODE_WIDTH + (arch_defs_pkg_OPERAND_WIDTH - 1)-:((arch_defs_pkg_OPERAND_WIDTH + 3) >= (arch_defs_pkg_OPERAND_WIDTH + 0) ? ((arch_defs_pkg_OPCODE_WIDTH + (arch_defs_pkg_OPERAND_WIDTH - 1)) - (arch_defs_pkg_OPERAND_WIDTH + 0)) + 1 : ((arch_defs_pkg_OPERAND_WIDTH + 0) - (arch_defs_pkg_OPCODE_WIDTH + (arch_defs_pkg_OPERAND_WIDTH - 1))) + 1)];
	assign operand = instruction[arch_defs_pkg_OPERAND_WIDTH - 1-:arch_defs_pkg_OPERAND_WIDTH];
endmodule
module register_nbit (
	clk,
	reset,
	load,
	data_in,
	latched_data
);
	localparam signed [31:0] arch_defs_pkg_DATA_WIDTH = 8;
	parameter N = arch_defs_pkg_DATA_WIDTH;
	input clk;
	input reset;
	input load;
	input [N - 1:0] data_in;
	output reg [N - 1:0] latched_data;
	always @(posedge clk)
		if (reset)
			latched_data <= {N {1'b0}};
		else if (load)
			latched_data <= data_in;
endmodule
module control_unit (
	clk,
	reset,
	opcode,
	flags,
	control_word
);
	reg _sv2v_0;
	input wire clk;
	input wire reset;
	localparam signed [31:0] arch_defs_pkg_OPCODE_WIDTH = 4;
	input wire [3:0] opcode;
	input wire [2:0] flags;
	output reg [22:0] control_word;
	reg [2:0] current_state = 3'd0;
	reg [2:0] next_state = 3'd0;
	reg [3:0] current_step;
	reg [3:0] next_step;
	always @(posedge clk)
		if (reset) begin
			current_state <= 3'd0;
			current_step <= 4'd0;
		end
		else begin
			current_state <= next_state;
			current_step <= next_step;
		end
	reg check_jump_condition = 1'b0;
	reg jump_condition_satisfied = 1'b0;
	reg [22:0] microcode_rom [0:15][0:7];
	always @(*) begin
		if (_sv2v_0)
			;
		next_state = current_state;
		next_step = current_step;
		control_word = 23'h000000;
		case (current_state)
			3'd0: next_state = 3'd1;
			3'd1: begin
				control_word = 23'h040000;
				next_state = 3'd2;
			end
			3'd2: begin
				control_word = 23'h048000;
				next_state = 3'd3;
			end
			3'd3: begin
				control_word = 23'h002000;
				next_state = 3'd4;
			end
			3'd4: begin
				control_word = 23'h122000;
				next_state = 3'd6;
			end
			3'd6: next_state = 3'd5;
			3'd5: begin
				control_word = microcode_rom[opcode][current_step];
				check_jump_condition = (control_word[7] || control_word[6]) || control_word[5];
				jump_condition_satisfied = ((control_word[7] && flags[0]) || (control_word[6] && flags[1])) || (control_word[5] && flags[2]);
				if (control_word[22]) begin
					next_state = 3'd7;
					next_step = 4'd0;
				end
				else if (check_jump_condition && !jump_condition_satisfied) begin
					control_word[19] = 1'b0;
					next_state = 3'd1;
					next_step = 4'd0;
				end
				else if (control_word[21]) begin
					next_state = 3'd1;
					next_step = 4'd0;
				end
				else
					next_step = current_step + 1;
			end
			3'd7: begin
				control_word = 23'h000000;
				next_state = 3'd7;
			end
			default: begin
				control_word = 23'h000000;
				next_state = 3'd7;
			end
		endcase
	end
	function automatic [3:0] sv2v_cast_953D0;
		input reg [3:0] inp;
		sv2v_cast_953D0 = inp;
	endfunction
	initial begin
		begin : sv2v_autoblock_1
			reg signed [31:0] i;
			for (i = 0; i < 16; i = i + 1)
				begin : sv2v_autoblock_2
					reg signed [31:0] s;
					for (s = 0; s < 8; s = s + 1)
						microcode_rom[i][s] = 23'h000000;
				end
		end
		microcode_rom[sv2v_cast_953D0(4'b0000)][4'd0] = 23'h200000;
		microcode_rom[sv2v_cast_953D0(4'b0001)][4'd0] = 23'h010000;
		microcode_rom[sv2v_cast_953D0(4'b0001)][4'd1] = 23'h018000;
		microcode_rom[sv2v_cast_953D0(4'b0001)][4'd2] = 23'h002000;
		microcode_rom[sv2v_cast_953D0(4'b0001)][4'd3] = 23'h202310;
		microcode_rom[sv2v_cast_953D0(4'b0010)][4'd0] = 23'h010000;
		microcode_rom[sv2v_cast_953D0(4'b0010)][4'd1] = 23'h018000;
		microcode_rom[sv2v_cast_953D0(4'b0010)][4'd2] = 23'h002000;
		microcode_rom[sv2v_cast_953D0(4'b0010)][4'd3] = 23'h202304;
		microcode_rom[sv2v_cast_953D0(4'b0011)][4'd0] = 23'h010000;
		microcode_rom[sv2v_cast_953D0(4'b0011)][4'd1] = 23'h018000;
		microcode_rom[sv2v_cast_953D0(4'b0011)][4'd2] = 23'h002000;
		microcode_rom[sv2v_cast_953D0(4'b0011)][4'd3] = 23'h002004;
		microcode_rom[sv2v_cast_953D0(4'b0011)][4'd4] = 23'h000600;
		microcode_rom[sv2v_cast_953D0(4'b0011)][4'd5] = 23'h200410;
		microcode_rom[sv2v_cast_953D0(4'b0100)][4'd0] = 23'h010000;
		microcode_rom[sv2v_cast_953D0(4'b0100)][4'd1] = 23'h018000;
		microcode_rom[sv2v_cast_953D0(4'b0100)][4'd2] = 23'h002000;
		microcode_rom[sv2v_cast_953D0(4'b0100)][4'd3] = 23'h002004;
		microcode_rom[sv2v_cast_953D0(4'b0100)][4'd4] = 23'h000e00;
		microcode_rom[sv2v_cast_953D0(4'b0100)][4'd5] = 23'h200410;
		microcode_rom[sv2v_cast_953D0(4'b0101)][4'd0] = 23'h010000;
		microcode_rom[sv2v_cast_953D0(4'b0101)][4'd1] = 23'h018000;
		microcode_rom[sv2v_cast_953D0(4'b0101)][4'd2] = 23'h002000;
		microcode_rom[sv2v_cast_953D0(4'b0101)][4'd3] = 23'h002004;
		microcode_rom[sv2v_cast_953D0(4'b0101)][4'd4] = 23'h001600;
		microcode_rom[sv2v_cast_953D0(4'b0101)][4'd5] = 23'h200410;
		microcode_rom[sv2v_cast_953D0(4'b0110)][4'd0] = 23'h010000;
		microcode_rom[sv2v_cast_953D0(4'b0110)][4'd1] = 23'h018000;
		microcode_rom[sv2v_cast_953D0(4'b0110)][4'd2] = 23'h002000;
		microcode_rom[sv2v_cast_953D0(4'b0110)][4'd3] = 23'h002004;
		microcode_rom[sv2v_cast_953D0(4'b0110)][4'd4] = 23'h001e00;
		microcode_rom[sv2v_cast_953D0(4'b0110)][4'd5] = 23'h200410;
		microcode_rom[sv2v_cast_953D0(4'b0111)][4'd0] = 23'h010000;
		microcode_rom[sv2v_cast_953D0(4'b0111)][4'd1] = 23'h018000;
		microcode_rom[sv2v_cast_953D0(4'b0111)][4'd2] = 23'h000008;
		microcode_rom[sv2v_cast_953D0(4'b0111)][4'd3] = 23'h204008;
		microcode_rom[sv2v_cast_953D0(4'b1000)][4'd0] = 23'h010000;
		microcode_rom[sv2v_cast_953D0(4'b1000)][4'd1] = 23'h210310;
		microcode_rom[sv2v_cast_953D0(4'b1001)][4'd0] = 23'h010000;
		microcode_rom[sv2v_cast_953D0(4'b1001)][4'd1] = 23'h290000;
		microcode_rom[sv2v_cast_953D0(4'b1010)][4'd0] = 23'h010000;
		microcode_rom[sv2v_cast_953D0(4'b1010)][4'd1] = 23'h290040;
		microcode_rom[sv2v_cast_953D0(4'b1011)][4'd0] = 23'h010000;
		microcode_rom[sv2v_cast_953D0(4'b1011)][4'd1] = 23'h290080;
		microcode_rom[sv2v_cast_953D0(4'b1100)][4'd0] = 23'h010000;
		microcode_rom[sv2v_cast_953D0(4'b1100)][4'd1] = 23'h290020;
		microcode_rom[sv2v_cast_953D0(4'b1101)][4'd0] = 23'h010000;
		microcode_rom[sv2v_cast_953D0(4'b1101)][4'd1] = 23'h018000;
		microcode_rom[sv2v_cast_953D0(4'b1101)][4'd2] = 23'h002000;
		microcode_rom[sv2v_cast_953D0(4'b1101)][4'd3] = 23'h202001;
		microcode_rom[sv2v_cast_953D0(4'b1110)][4'd0] = 23'h000008;
		microcode_rom[sv2v_cast_953D0(4'b1110)][4'd1] = 23'h200009;
		microcode_rom[sv2v_cast_953D0(4'b1111)][4'd0] = 23'h000000;
		microcode_rom[sv2v_cast_953D0(4'b1111)][4'd1] = 23'h600000;
	end
	initial _sv2v_0 = 0;
endmodule
module cpu (
	clk,
	reset,
	out_val,
	flag_zero_o,
	flag_carry_o,
	flag_negative_o,
	debug_out_B,
	debug_out_IR,
	debug_out_PC
);
	reg _sv2v_0;
	input wire clk;
	input wire reset;
	localparam signed [31:0] arch_defs_pkg_DATA_WIDTH = 8;
	output wire [7:0] out_val;
	output wire flag_zero_o;
	output wire flag_carry_o;
	output wire flag_negative_o;
	output wire [7:0] debug_out_B;
	output wire [7:0] debug_out_IR;
	localparam signed [31:0] arch_defs_pkg_ADDR_WIDTH = 4;
	output wire [3:0] debug_out_PC;
	wire [7:0] b_out;
	assign debug_out_B = b_out;
	localparam signed [31:0] arch_defs_pkg_OPCODE_WIDTH = 4;
	wire [3:0] opcode;
	localparam signed [31:0] arch_defs_pkg_OPERAND_WIDTH = arch_defs_pkg_DATA_WIDTH - arch_defs_pkg_OPCODE_WIDTH;
	wire [arch_defs_pkg_OPERAND_WIDTH - 1:0] operand;
	assign debug_out_IR = {opcode, operand};
	wire [7:0] counter_out;
	assign debug_out_PC = counter_out;
	wire [1:0] alu_op;
	reg [22:0] control_word = 23'h000000;
	wire halt;
	wire pc_enable;
	wire load_o;
	wire load_a;
	wire load_b;
	wire load_ir;
	wire load_pc;
	wire load_flags;
	wire load_sets_zn;
	wire load_ram;
	wire load_mar;
	wire oe_a;
	wire oe_alu;
	wire oe_ir;
	wire oe_pc;
	wire oe_ram;
	wire [7:0] bus;
	wire [7:0] o_out;
	wire [7:0] a_out;
	wire [7:0] alu_out;
	wire [7:0] ram_out;
	wire [7:0] memory_address_out;
	assign bus = (oe_pc ? {{arch_defs_pkg_DATA_WIDTH - arch_defs_pkg_ADDR_WIDTH {1'b0}}, counter_out} : (oe_ram ? ram_out : (oe_ir ? {{arch_defs_pkg_DATA_WIDTH - arch_defs_pkg_OPERAND_WIDTH {1'b0}}, operand} : (oe_alu ? alu_out : (oe_a ? a_out : {arch_defs_pkg_DATA_WIDTH {1'b0}})))));
	program_counter u_program_counter(
		.clk(clk),
		.reset(reset),
		.enable(pc_enable),
		.load(load_pc),
		.counter_in(bus[3:0]),
		.counter_out(counter_out)
	);
	register_nbit #(.N(arch_defs_pkg_DATA_WIDTH)) u_register_OUT(
		.clk(clk),
		.reset(reset),
		.load(load_o),
		.data_in(bus),
		.latched_data(o_out)
	);
	assign out_val = o_out;
	register_nbit #(.N(arch_defs_pkg_DATA_WIDTH)) u_register_A(
		.clk(clk),
		.reset(reset),
		.load(load_a),
		.data_in(bus),
		.latched_data(a_out)
	);
	register_nbit #(.N(arch_defs_pkg_DATA_WIDTH)) u_register_B(
		.clk(clk),
		.reset(reset),
		.load(load_b),
		.data_in(bus),
		.latched_data(b_out)
	);
	register_nbit #(.N(arch_defs_pkg_ADDR_WIDTH)) u_register_memory_address(
		.clk(clk),
		.reset(reset),
		.load(load_mar),
		.data_in(bus[3:0]),
		.latched_data(memory_address_out)
	);
	register_instruction u_register_instr(
		.clk(clk),
		.reset(reset),
		.load(load_ir),
		.data_in(bus),
		.opcode(opcode),
		.operand(operand)
	);
	localparam signed [31:0] arch_defs_pkg_FLAG_COUNT = 3;
	(* keep *) wire [2:0] flags_out;
	reg C_in;
	reg N_in;
	reg Z_in;
	register_nbit #(.N(arch_defs_pkg_FLAG_COUNT)) u_register_flags(
		.clk(clk),
		.reset(reset),
		.load(load_flags),
		.data_in({N_in, C_in, Z_in}),
		.latched_data(flags_out)
	);
	assign flag_zero_o = flags_out[0];
	assign flag_carry_o = flags_out[1];
	assign flag_negative_o = flags_out[2];
	wire [23:1] sv2v_tmp_u_control_unit_control_word;
	always @(*) control_word = sv2v_tmp_u_control_unit_control_word;
	control_unit u_control_unit(
		.clk(clk),
		.reset(reset),
		.opcode(opcode),
		.flags(flags_out),
		.control_word(sv2v_tmp_u_control_unit_control_word)
	);
	assign load_o = control_word[0];
	assign load_a = control_word[4];
	assign load_b = control_word[2];
	assign load_ir = control_word[17];
	assign load_pc = control_word[19];
	assign load_mar = control_word[15];
	assign load_ram = control_word[14];
	assign oe_a = control_word[3];
	assign oe_ir = control_word[16];
	assign oe_pc = control_word[18];
	assign oe_alu = control_word[10];
	assign oe_ram = control_word[13];
	assign alu_op = control_word[12-:2];
	assign pc_enable = control_word[20];
	assign halt = control_word[22];
	assign load_flags = control_word[9];
	assign load_sets_zn = control_word[8];
	wire flag_alu_carry;
	wire flag_alu_negative;
	wire flag_alu_zero;
	alu u_alu(
		.clk(clk),
		.reset(reset),
		.a_in(a_out),
		.b_in(b_out),
		.alu_op(alu_op),
		.latched_result(alu_out),
		.zero_flag(flag_alu_zero),
		.carry_flag(flag_alu_carry),
		.negative_flag(flag_alu_negative)
	);
	ram u_ram(
		.clk(clk),
		.we(load_ram),
		.address(memory_address_out),
		.data_in(bus),
		.data_out(ram_out)
	);
	reg load_data_is_zero;
	reg load_data_is_negative;
	function automatic [3:0] sv2v_cast_953D0;
		input reg [3:0] inp;
		sv2v_cast_953D0 = inp;
	endfunction
	always @(*) begin
		if (_sv2v_0)
			;
		load_data_is_zero = 1'b0;
		load_data_is_negative = 1'b0;
		if (load_sets_zn)
			(* full_case, parallel_case *)
			case (opcode)
				sv2v_cast_953D0(4'b1000): begin
					load_data_is_zero = operand == {arch_defs_pkg_OPERAND_WIDTH {1'b0}};
					load_data_is_negative = operand[arch_defs_pkg_OPERAND_WIDTH - 1];
				end
				sv2v_cast_953D0(4'b0001): begin
					load_data_is_zero = bus == {arch_defs_pkg_DATA_WIDTH {1'b0}};
					load_data_is_negative = bus[7];
				end
				sv2v_cast_953D0(4'b0010): begin
					load_data_is_zero = bus == {arch_defs_pkg_DATA_WIDTH {1'b0}};
					load_data_is_negative = bus[7];
				end
				default: begin
					load_data_is_zero = 1'b0;
					load_data_is_negative = 1'b0;
				end
			endcase
	end
	always @(*) begin
		if (_sv2v_0)
			;
		Z_in = flag_alu_zero;
		N_in = flag_alu_negative;
		C_in = flag_alu_carry;
		if (load_sets_zn) begin
			Z_in = load_data_is_zero;
			N_in = load_data_is_negative;
			C_in = 1'b0;
		end
	end
	initial _sv2v_0 = 0;
endmodule
module alu_tb;
	reg clk;
	reg reset;
	localparam signed [31:0] arch_defs_pkg_DATA_WIDTH = 8;
	reg [7:0] tb_a_in;
	reg [7:0] tb_b_in;
	reg [1:0] tb_alu_op;
	wire [7:0] dut_latched_result;
	wire dut_zero_flag;
	wire dut_carry_flag;
	wire dut_negative_flag;
	alu uut(
		.clk(clk),
		.reset(reset),
		.a_in(tb_a_in),
		.b_in(tb_b_in),
		.alu_op(tb_alu_op),
		.latched_result(dut_latched_result),
		.zero_flag(dut_zero_flag),
		.carry_flag(dut_carry_flag),
		.negative_flag(dut_negative_flag)
	);
	initial begin
		clk = 0;
		forever #(5) clk = ~clk;
	end
	task test_utils_pkg_pretty_print_assert_vec;
		input [31:0] actual;
		input [31:0] expected;
		input string msg;
		if (actual !== expected)
			$display("\033[0;31mAssertion Failed: %s. Actual: %h, Expected: %h\033[0m", msg, actual, expected);
		else
			$display("\033[0;32mAssertion Passed: %s\033[0m", msg);
	endtask
	task apply_and_check;
		input [7:0] a;
		input [7:0] b;
		input reg [1:0] op;
		input string op_name;
		input [7:0] exp_result;
		input reg exp_c;
		input reg exp_z;
		input reg exp_n;
		input string description;
		begin
			@(negedge clk)
				;
			tb_a_in = a;
			tb_b_in = b;
			tb_alu_op = op;
			$display("Applying: %s (A=%h, B=%h, Op=%s)", description, a, b, op_name);
			@(posedge clk)
				;
			#(1)
				;
			test_utils_pkg_pretty_print_assert_vec(dut_latched_result, exp_result, $sformatf("%s - Result", description));
			test_utils_pkg_pretty_print_assert_vec(dut_carry_flag, exp_c, $sformatf("%s - Carry Flag", description));
			test_utils_pkg_pretty_print_assert_vec(dut_zero_flag, exp_z, $sformatf("%s - Zero Flag", description));
			test_utils_pkg_pretty_print_assert_vec(dut_negative_flag, exp_n, $sformatf("%s - Negative Flag", description));
			$display("----------------------------------------");
		end
	endtask
	initial begin
		$dumpfile("waveform.vcd");
		$dumpvars(0, alu_tb);
		$display("--- ALU Testbench Start ---");
		reset = 1;
		tb_a_in = 1'sbx;
		tb_b_in = 1'sbx;
		tb_alu_op = 1'sbx;
		@(posedge clk)
			;
		#(1)
			;
		test_utils_pkg_pretty_print_assert_vec(dut_latched_result, {arch_defs_pkg_DATA_WIDTH {1'b0}}, "Reset - Result");
		$display("Reset Applied");
		@(negedge clk)
			;
		reset = 0;
		$display("Reset Released");
		$display("----------------------------------------");
		@(posedge clk)
			;
		#(1)
			;
		apply_and_check(8'h05, 8'h03, 2'b00, "ADD", 8'h08, 1'b0, 1'b0, 1'b0, "ADD: 5 + 3");
		apply_and_check(8'h00, 8'h00, 2'b00, "ADD", 8'h00, 1'b0, 1'b1, 1'b0, "ADD: 0 + 0");
		apply_and_check(8'hff, 8'h01, 2'b00, "ADD", 8'h00, 1'b1, 1'b1, 1'b0, "ADD: 255 + 1");
		apply_and_check(8'h80, 8'h01, 2'b00, "ADD", 8'h81, 1'b0, 1'b0, 1'b1, "ADD: 128 + 1");
		apply_and_check(8'h7f, 8'h01, 2'b00, "ADD", 8'h80, 1'b0, 1'b0, 1'b1, "ADD: 127 + 1");
		apply_and_check(8'hf0, 8'hf0, 2'b00, "ADD", 8'he0, 1'b1, 1'b0, 1'b1, "ADD: 240 + 240");
		apply_and_check(8'h08, 8'h03, 2'b01, "SUB", 8'h05, 1'b1, 1'b0, 1'b0, "SUB: 8 - 3");
		apply_and_check(8'h05, 8'h05, 2'b01, "SUB", 8'h00, 1'b1, 1'b1, 1'b0, "SUB: 5 - 5");
		apply_and_check(8'h03, 8'h05, 2'b01, "SUB", 8'hfe, 1'b0, 1'b0, 1'b1, "SUB: 3 - 5");
		apply_and_check(8'h00, 8'h01, 2'b01, "SUB", 8'hff, 1'b0, 1'b0, 1'b1, "SUB: 0 - 1");
		apply_and_check(8'h80, 8'h01, 2'b01, "SUB", 8'h7f, 1'b1, 1'b0, 1'b0, "SUB: -128 - 1");
		apply_and_check(8'h55, 8'haa, 2'b10, "AND", 8'h00, 1'b0, 1'b1, 1'b0, "AND: 55 & AA");
		apply_and_check(8'hcd, 8'hff, 2'b10, "AND", 8'hcd, 1'b0, 1'b0, 1'b1, "AND: CD & FF");
		apply_and_check(8'hcd, 8'h0f, 2'b10, "AND", 8'h0d, 1'b0, 1'b0, 1'b0, "AND: CD & 0F");
		apply_and_check(8'hf0, 8'h0f, 2'b10, "AND", 8'h00, 1'b0, 1'b1, 1'b0, "AND: F0 & 0F");
		apply_and_check(8'h55, 8'haa, 2'b11, "OR", 8'hff, 1'b0, 1'b0, 1'b1, "OR: 55 | AA");
		apply_and_check(8'hcd, 8'h00, 2'b11, "OR", 8'hcd, 1'b0, 1'b0, 1'b1, "OR: CD | 00");
		apply_and_check(8'h0f, 8'h00, 2'b11, "OR", 8'h0f, 1'b0, 1'b0, 1'b0, "OR: 0F | 00");
		apply_and_check(8'hf0, 8'h0f, 2'b11, "OR", 8'hff, 1'b0, 1'b0, 1'b1, "OR: F0 | 0F");
		$display("--- ALU Testbench Complete ---");
		@(posedge clk)
			;
		$finish;
	end
endmodule

build/waveform.vcd
$date
	Sun Apr 20 09:34:58 2025
$end
$version
	Icarus Verilog
$end
$timescale
	1ps
$end
$scope module alu_tb $end
$var wire 1 ! dut_zero_flag $end
$var wire 1 " dut_negative_flag $end
$var wire 8 # dut_latched_result [7:0] $end
$var wire 1 $ dut_carry_flag $end
$var parameter 32 % arch_defs_pkg_DATA_WIDTH $end
$var reg 1 & clk $end
$var reg 1 ' reset $end
$var reg 8 ( tb_a_in [7:0] $end
$var reg 2 ) tb_alu_op [1:0] $end
$var reg 8 * tb_b_in [7:0] $end
$scope module uut $end
$var wire 8 + a_in [7:0] $end
$var wire 2 , alu_op [1:0] $end
$var wire 8 - b_in [7:0] $end
$var wire 1 $ carry_flag $end
$var wire 1 & clk $end
$var wire 1 ' reset $end
$var wire 1 ! zero_flag $end
$var wire 1 " negative_flag $end
$var parameter 32 . arch_defs_pkg_DATA_WIDTH $end
$var reg 1 / _sv2v_0 $end
$var reg 9 0 comb_arith_result_i [8:0] $end
$var reg 1 1 comb_carry_out_i $end
$var reg 8 2 comb_result_final_i [7:0] $end
$var reg 8 3 comp_logic_result_i [7:0] $end
$var reg 8 4 latched_result [7:0] $end
$upscope $end
$scope task apply_and_check $end
$var reg 8 5 a [7:0] $end
$var reg 8 6 b [7:0] $end
$var reg 1 7 exp_c $end
$var reg 1 8 exp_n $end
$var reg 8 9 exp_result [7:0] $end
$var reg 1 : exp_z $end
$var reg 2 ; op [1:0] $end
$upscope $end
$scope task test_utils_pkg_pretty_print_assert_vec $end
$var reg 32 < actual [31:0] $end
$var reg 32 = expected [31:0] $end
$upscope $end
$upscope $end
$enddefinitions $end
$comment Show the parameter values. $end
$dumpall
b1000 .
b1000 %
$end
#0
$dumpvars
bx =
bx <
bx ;
x:
bx 9
x8
x7
bx 6
bx 5
bx 4
b0 3
b0 2
01
b0 0
0/
bx -
bx ,
bx +
bx *
bx )
bx (
1'
0&
0$
bx #
0"
1!
$end
#5000
b0 #
b0 4
1&
#6000
b0 =
b0 <
#10000
0'
0&
#15000
1&
#16000
08
0:
07
b1000 9
b0 ;
b11 6
b101 5
#20000
0!
b1000 2
b1000 0
b0 )
b0 ,
b11 *
b11 -
b101 (
b101 +
0&
#25000
b1000 #
b1000 4
1&
#26000
1:
b0 9
b0 6
b0 5
b0 =
b0 <
#30000
1!
b0 2
b0 0
b0 *
b0 -
b0 (
b0 +
0&
#35000
b0 #
b0 4
1&
#36000
17
b1 6
b11111111 5
b0 =
b0 <
#40000
1$
11
b100000000 0
b1 *
b1 -
b11111111 (
b11111111 +
0&
#45000
1&
#46000
18
0:
07
b10000001 9
b10000000 5
b0 =
b0 <
#50000
1"
0!
b10000001 2
0$
01
b10000001 0
b10000000 (
b10000000 +
0&
#55000
b10000001 #
b10000001 4
1&
#56000
b10000000 9
b1111111 5
b1 =
b1 <
#60000
0!
b10000000 2
b10000000 0
b1111111 (
b1111111 +
0&
#65000
b10000000 #
b10000000 4
1&
#66000
17
b11100000 9
b11110000 6
b11110000 5
b1 =
b1 <
#70000
1$
11
0!
b11100000 2
b111100000 0
b11110000 *
b11110000 -
b11110000 (
b11110000 +
0&
#75000
b11100000 #
b11100000 4
1&
#76000
08
b101 9
b1 ;
b11 6
b1000 5
b1 =
b1 <
#80000
0"
0!
b101 2
1$
11
b100000101 0
b1 )
b1 ,
b11 *
b11 -
b1000 (
b1000 +
0&
#85000
b101 #
b101 4
1&
#86000
1:
b0 9
b101 6
b101 5
b0 =
b0 <
#90000
1!
b0 2
1$
11
b100000000 0
b101 *
b101 -
b101 (
b101 +
0&
#95000
b0 #
b0 4
1&
#96000
18
0:
07
b11111110 9
b11 5
b0 =
b0 <
#100000
1"
0!
b11111110 2
0$
01
b11111110 0
b11 (
b11 +
0&
#105000
b11111110 #
b11111110 4
1&
#106000
b11111111 9
b1 6
b0 5
b1 =
b1 <
#110000
0!
b11111111 2
b11111111 0
b1 *
b1 -
b0 (
b0 +
0&
#115000
b11111111 #
b11111111 4
1&
#116000
08
17
b1111111 9
b10000000 5
b1 =
b1 <
#120000
0"
1$
11
0!
b1111111 2
b101111111 0
b10000000 (
b10000000 +
0&
#125000
b1111111 #
b1111111 4
1&
#126000
1:
07
b0 9
b10 ;
b10101010 6
b1010101 5
b0 =
b0 <
#130000
1!
b0 2
0$
01
b0 0
b10 )
b10 ,
b10101010 *
b10101010 -
b1010101 (
b1010101 +
0&
#135000
b0 #
b0 4
1&
#136000
18
0:
b11001101 9
b11111111 6
b11001101 5
b0 =
b0 <
#140000
1"
0!
b11001101 2
b11001101 3
b11111111 *
b11111111 -
b11001101 (
b11001101 +
0&
#145000
b11001101 #
b11001101 4
1&
#146000
08
b1101 9
b1111 6
b1 =
b1 <
#150000
0"
0!
b1101 2
b1101 3
b1111 *
b1111 -
0&
#155000
b1101 #
b1101 4
1&
#156000
1:
b0 9
b11110000 5
b0 =
b0 <
#160000
1!
b0 2
b0 3
b11110000 (
b11110000 +
0&
#165000
b0 #
b0 4
1&
#166000
18
0:
b11111111 9
b11 ;
b10101010 6
b1010101 5
b0 =
b0 <
#170000
1"
0!
b11111111 2
b11111111 3
b11 )
b11 ,
b10101010 *
b10101010 -
b1010101 (
b1010101 +
0&
#175000
b11111111 #
b11111111 4
1&
#176000
b11001101 9
b0 6
b11001101 5
b1 =
b1 <
#180000
0!
b11001101 2
b11001101 3
b0 *
b0 -
b11001101 (
b11001101 +
0&
#185000
b11001101 #
b11001101 4
1&
#186000
08
b1111 9
b1111 5
b1 =
b1 <
#190000
0"
0!
b1111 2
b1111 3
b1111 (
b1111 +
0&
#195000
b1111 #
b1111 4
1&
#196000
18
b11111111 9
b1111 6
b11110000 5
b0 =
b0 <
#200000
1"
0!
b11111111 2
b11111111 3
b1111 *
b1111 -
b11110000 (
b11110000 +
0&
#205000
b11111111 #
b11111111 4
1&
#206000
b1 =
b1 <
